Workbook

Sheet Category budget
A1: category | B1: amount | D1: =SUM(B2:B11) -> 108500
A2: house rent | B2: 10000
A3: food & grocery | B3: 10000
A4: commute | B4: 2000
A5: insurance | B5: 50000
A6: utilities | B6: 20000
A7: mobile | B7: 1500
A8: internet | B8: 1000
A9: grooming | B9: 1000
A10: others | B10: 10000
A11: entertainment | B11: 3000

Sheet Expence Journal
A1: Year | B1: Item | C1: Amount (₹) | D1: Day | E1: Month | F1: Category | G1: Notes
A2: 2025 | B2: ATM | C2: 58000 | D2: 45906 | E2: sep | F2: =VLOOKUP(B2,'Item & Category'!$A$1:$B$256,2,FALSE) -> Cash Withdrawal
A3: 2025 | B3: atm | C3: 42000 | D3: 45908 | E3: sep | F3: =VLOOKUP(B3,'Item & Category'!$A$1:$B$256,2,FALSE) -> Cash Withdrawal
A4: 2025 | B4: restaurant | C4: 5000 | D4: 45908 | E4: sep | F4: =VLOOKUP(B4,'Item & Category'!$A$1:$B$256,2,FALSE) -> Food and Grocery
A5: 2025 | B5: electricals | C5: 1300 | D5: 45908 | E5: sep | F5: =VLOOKUP(B5,'Item & Category'!$A$1:$B$256,2,FALSE) -> Furnishing
A6: 2025 | B6: mutual funds | C6: 9000 | D6: 45911 | E6: sep | F6: =VLOOKUP(B6,'Item & Category'!$A$1:$B$256,2,FALSE) -> Investments
A7: 2025 | B7: medical | C7: 1100 | D7: 45911 | E7: sep | F7: =VLOOKUP(B7,'Item & Category'!$A$1:$B$256,2,FALSE) -> Medical
A8: 2025 | B8: coffee | C8: 150 | D8: 45911 | E8: sep | F8: =VLOOKUP(B8,'Item & Category'!$A$1:$B$256,2,FALSE) -> Food and Grocery
A9: 2025 | B9: insurance | C9: 25000 | D9: 45911 | E9: sep | F9: =VLOOKUP(B9,'Item & Category'!$A$1:$B$256,2,FALSE) -> Insurance
A10: 2025 | B10: hair cut | C10: 500 | D10: 45912 | E10: sep | F10: =VLOOKUP(B10,'Item & Category'!$A$1:$B$256,2,FALSE) -> Grooming
A11: 2025 | B11: coin | C11: 5000 | D11: 45912 | E11: sep | F11: =VLOOKUP(B11,'Item & Category'!$A$1:$B$256,2,FALSE) -> Investments
A12: 2025 | B12: kite | C12: 2000 | D12: 45912 | E12: sep | F12: =VLOOKUP(B12,'Item & Category'!$A$1:$B$256,2,FALSE) -> Investments
A13: 2025 | B13: angelone | C13: 5000 | D13: 45913 | E13: sep | F13: =VLOOKUP(B13,'Item & Category'!$A$1:$B$256,2,FALSE) -> Investments
... A98: 2025 | B98: gym | C98: 244.16 | D98: 45952 | E98: oct | F98: =VLOOKUP(B98,'Item & Category'!$A$1:$B$256,2,FALSE) -> Fitness
A99: 2025 | B99: gold | C99: 1,00,000.00 | D99: 45952 | E99: oct | F99: =VLOOKUP(B99,'Item & Category'!$A$1:$B$256,2,FALSE) -> Gold
A100: 2025 | B100: Grocery | C100: 10500 | D100: 45952 | E100: oct | F100: =VLOOKUP(B100,'Item & Category'!$A$1:$B$256,2,FALSE) -> Food and Grocery
A101: 2025 | B101: coffee | C101: 194.16 | D101: 45952 | E101: oct | F101: =VLOOKUP(B101,'Item & Category'!$A$1:$B$256,2,FALSE) -> Food and Grocery
A102: 2025 | B102: cinema | C102: 3000 | D102: 45953 | E102: oct | F102: =VLOOKUP(B102,'Item & Category'!$A$1:$B$256,2,FALSE) -> Entertainment
A103: 2025 | B103: zomato | C103: 3495 | D103: 45953 | E103: oct | F103: =VLOOKUP(B103,'Item & Category'!$A$1:$B$256,2,FALSE) -> Food and Grocery
A104: 2025 | B104: bus pass | C104: 20 | D104: 45953 | E104: oct | F104: =VLOOKUP(B104,'Item & Category'!$A$1:$B$256,2,FALSE) -> Commute
A105: 2025 | B105: bus pass | C105: 20 | D105: 45953 | E105: oct | F105: =VLOOKUP(B105,'Item & Category'!$A$1:$B$256,2,FALSE) -> Commute
A106: 2025 | B106: rent | C106: 30000 | D106: 45954 | E106: oct | F106: =VLOOKUP(B106,'Item & Category'!$A$1:$B$256,2,FALSE) -> House Rent
A107: 2025 | B107: BigBasket | C107: 1400 | D107: 45954 | E107: oct | F107: =VLOOKUP(B107,'Item & Category'!$A$1:$B$256,2,FALSE) -> Food and Grocery
A108: 2025 | B108: power | C108: 661 | D108: 45955 | E108: oct | F108: =VLOOKUP(B108,'Item & Category'!$A$1:$B$256,2,FALSE) -> Utility Bills
A109: 2025 | B109: bus pass | C109: 1000 | D109: 45955 | E109: oct | F109: =VLOOKUP(B109,'Item & Category'!$A$1:$B$256,2,FALSE) -> Commute
A110: 2025 | B110: coffee | C110: 1000 | D110: 45955 | E110: oct | F110: =VLOOKUP(B110,'Item & Category'!$A$1:$B$256,2,FALSE) -> Food and Grocery
A111: 2025 | B111: medical | C111: 1500 | D111: 45955 | E111: oct | F111: =VLOOKUP(B111,'Item & Category'!$A$1:$B$256,2,FALSE) -> Medical
... A120: 2025 | B120: petrol | C120: 250 | D120: 45960 | E120: oct | F120: =VLOOKUP(B120,'Item & Category'!$A$1:$B$256,2,FALSE) -> Commute
A121: 2025
A122: 2025
A123: 2025
A124: 2025
A125: 2025
A126: 2025
A127: 2025
A128: 2025
A129: 2025
A130: 2025
A131: 2025
A132: 2025
... A135: 2025

Sheet Summary of 2025
A1: Sum of Amount (₹) | B1: Column Labels
A2: Row Labels | B2: sep | C2: oct | D2: Grand Total
A3: Activity | B3: 300 | C3: 150 | D3: 450
A4: boating | B4: 300 | C4: 150 | D4: 450
A5: Cash Withdrawal | B5: 100000 | C5: 7945.54 | D5: 107945.54
A6: ATM | B6: 100000 | C6: 7945.54 | D6: 107945.54
A7: Charges | B7: 200 | D7: 200
A8: bank charges | B8: 200 | D8: 200
A9: Clothing | C9: 2500 | D9: 2500
A10: cloth shopping | C10: 2500 | D10: 2500
A11: Commute | B11: 15510 | C11: 9906.46 | D11: 25416.46
A12: bus pass | B12: 410 | C12: 1728.92 | D12: 2138.92
A13: petrol | B13: 15000 | C13: 6832.54 | D13: 21832.54
A14: train pass | B14: 100 | C14: 1345 | D14: 1445
A15: Entertainment | B15: 2813 | C15: 7340 | D15: 10153
A16: activity | B16: 299 | C16: 2300 | D16: 2599
A17: amazon prime | B17: 200 | D17: 200
A18: cinema | B18: 821 | C18: 3000 | D18: 3821
A19: museum | B19: 500 | C19: 600 | D19: 1100
A20: netflix | B20: 200 | C20: 1440 | D20: 1640
A21: theme park | B21: 793 | D21: 793
A22: Fitness | B22: 1978.01 | C22: 1148.84 | D22: 3126.85
A23: gym | B23: 1978.01 | C23: 1148.84 | D23: 3126.85
A24: Food and Grocery | B24: 6469.5 | C24: 19110.39 | D24: 25579.89
A25: BigBasket | C25: 1400 | D25: 1400
A26: coffee | B26: 290 | C26: 1795.33 | D26: 2085.33
A27: Grocery | C27: 10500 | D27: 10500
A28: icecream | B28: 300 | D28: 300
A29: indian grocery | B29: 179.5 | C29: 1500 | D29: 1679.5
A30: pizza | B30: 500 | D30: 500
A31: reliance supermarket | C31: 420.06 | D31: 420.06
A32: restaurant | B32: 5000 | D32: 5000
A33: swiggy | B33: 200 | D33: 200
A34: zomato | C34: 3495 | D34: 3495
A35: Furnishing | B35: 15300 | D35: 15300
A36: electricals | B36: 1300 | D36: 1300
A37: washing machine | B37: 14000 | D37: 14000
A38: Gadgets | B38: 2899 | D38: 2899
A39: mobile | B39: 2899 | D39: 2899
A40: Gift | B40: 2456.17 | C40: 9000 | D40: 11456.17
A41: gift | B41: 2456.17 | C41: 9000 | D41: 11456.17
A42: Gold | B42: 69150 | C42: 21556.249 | D42: 90706.249
A43: gold | B43: 14000 | C43: 14000 | D43: 28000
A44: goldbees | B44: 50000 | C44: 7556.2494 | D44: 57556.249
A45: sgb | B45: 5150 | D45: 5150
A46: Grooming | B46: 1240 | C46: 1729.4 | D46: 2969.4
A47: hair cut | B47: 500 | C47: 1470.4 | D47: 1970.4
A48: trim | B48: 740 | C48: 259 | D48: 999
A49: House Rent | C49: 41500 | D49: 41500
A50: rent | C50: 41500 | D50: 41500
A51: Household | B51: 2000 | C51: 7000 | D51: 9000
A52: household | B52: 2000 | C52: 7000 | D52: 9000
A53: Insurance | B53: 39000 | C53: 58400 | D53: 97400
A54: insurance | B54: 39000 | C54: 58400 | D54: 97400
A55: Investments | B55: 81100 | C55: 52149.59 | D55: 133249.59
A56: angelone | B56: 5000 | D56: 5000
A57: coin | B57: 5000 | D57: 5000
A58: groww | B58: 5100 | C58: 20000 | D58: 25100
A59: kite | B59: 2000 | D59: 2000
A60: mutual funds | B60: 9000 | C60: 7200 | D60: 16200
A61: stocks | C61: 18449.59 | D61: 18449.59
A62: upstox | B62: 5000 | D62: 5000
A63: zerodha | B63: 50000 | C63: 6500 | D63: 56500
A64: Medical | B64: 1400 | C64: 6700 | D64: 8100
A65: medical | B65: 1400 | C65: 6700 | D65: 8100
A66: Mobile & Internet | B66: 3390 | C66: 2446 | D66: 5836
A67: airtel | C67: 850 | D67: 850
A68: internet | B68: 200 | C68: 200 | D68: 400
A69: jio | B69: 690 | C69: 200 | D69: 890
A70: sim card | B70: 2500 | D70: 2500
A71: vodafone | C71: 1196 | D71: 1196
A72: Tour | B72: 27000 | C72: 19300 | D72: 46300
A73: tour | C73: 6500 | D73: 6500
A74: trip | B74: 27000 | C74: 12800 | D74: 39800
A75: Unexpected | B75: 50000 | D75: 50000
A76: emergency | B76: 50000 | D76: 50000
A77: Utility Bills | B77: 3400 | C77: 32171 | D77: 35571
A78: gas | B78: 2000 | D78: 2000
A79: power | B79: 400 | C79: 5671 | D79: 6071
A80: water bill | B80: 500 | C80: 13500 | D80: 14000
A81: water tax | B81: 500 | C81: 13000 | D81: 13500
A82: Grand Total | B82: 425605.68 | C82: 300053.47 | D82: 725659.15

Sheet Item & Category
A1: Item Name | B1: Category
A2: Boating | B2: Activity
A3: Skating | B3: Activity
A4: ATM | B4: Cash Withdrawal
A5: Bank charges | B5: Charges
A6: Cloth Shopping | B6: Clothing
A7: Train Pass | B7: Commute
A8: Petrol | B8: Commute
A9: Bus Pass | B9: Commute
A10: Amazon Prime | B10: Entertainment
A11: Netflix | B11: Entertainment
A12: Cinema | B12: Entertainment
... A80: Water tax | B80: Utility Bills
